setup.py
client/__init__.py
client/client.py
client/descryptors.py
client/metaclasses.py
client/client_/__init__.py
client/client_/add_contact.py
client/client_/database.py
client/client_/del_contact.py
client/client_/main_window.py
client/client_/start_dialog.py
client/client_/transport.py
client/common/__init__.py
client/common/decos.py
client/common/utils.py
client/common/variables.py
client/logs/__init__.py
client/logs/config_client_log.py
client/logs/config_server_log.py
messenger_client_kinder.egg-info/PKG-INFO
messenger_client_kinder.egg-info/SOURCES.txt
messenger_client_kinder.egg-info/dependency_links.txt
messenger_client_kinder.egg-info/requires.txt
messenger_client_kinder.egg-info/top_level.txt