Metadata-Version: 1.0
Name: messenger-client-kinder
Version: 0.0.1
Summary: mess_server_Kinder
Home-page: UNKNOWN
Author: Ivan Kinder
Author-email: example@example.com
License: UNKNOWN
Platform: UNKNOWN
